README.md
setup.py
karamel/__init__.py
karamel/exception.py
karamel/logger.py
karamel/packages.py
karamel.egg-info/PKG-INFO
karamel.egg-info/SOURCES.txt
karamel.egg-info/dependency_links.txt
karamel.egg-info/requires.txt
karamel.egg-info/top_level.txt
karamel/command/__init__.py
karamel/command/command.py
karamel/command/freeze.py
karamel/command/install.py
karamel/command/list.py
karamel/command/search.py
karamel/command/uninstall.py
karamel/command/update.py
scripts/karamel