Metadata-Version: 1.0
Name: karamel
Version: 0.2.1
Summary: Karamel is a library that help you build powerful Package Manager based on Git.
Home-page: https://gitlab.com/karamel/karamel
Author: Noel Martignoni
Author-email: noel@martignoni.fr
License: UNKNOWN
Platform: UNKNOWN
